langchain/__init__.py
langchain/py.typed
langchain/agents/__init__.py
langchain/agents/factory.py
langchain/agents/structured_output.py
langchain/agents/middleware/__init__.py
langchain/agents/middleware/_execution.py
langchain/agents/middleware/_redaction.py
langchain/agents/middleware/_retry.py
langchain/agents/middleware/context_editing.py
langchain/agents/middleware/file_search.py
langchain/agents/middleware/human_in_the_loop.py
langchain/agents/middleware/model_call_limit.py
langchain/agents/middleware/model_fallback.py
langchain/agents/middleware/model_retry.py
langchain/agents/middleware/pii.py
langchain/agents/middleware/shell_tool.py
langchain/agents/middleware/summarization.py
langchain/agents/middleware/todo.py
langchain/agents/middleware/tool_call_limit.py
langchain/agents/middleware/tool_emulator.py
langchain/agents/middleware/tool_retry.py
langchain/agents/middleware/tool_selection.py
langchain/agents/middleware/types.py
langchain/chat_models/__init__.py
langchain/chat_models/base.py
langchain/embeddings/__init__.py
langchain/embeddings/base.py
langchain/messages/__init__.py
langchain/rate_limiters/__init__.py
langchain/tools/__init__.py
langchain/tools/tool_node.py
langchain-1.1.1.dist-info/METADATA
langchain-1.1.1.dist-info/WHEEL
langchain-1.1.1.dist-info/licenses/LICENSE
langchain-1.1.1.dist-info/RECORD
