Metadata-Version: 2.4
Name: langchain
Version: 1.1.1
Summary: Building applications with LLMs through composability
Project-URL: Homepage, https://docs.langchain.com/
Project-URL: Documentation, https://reference.langchain.com/python/langchain/langchain/
Project-URL: Source, https://github.com/langchain-ai/langchain/tree/master/libs/langchain
Project-URL: Changelog, https://github.com/langchain-ai/langchain/releases?q=tag%3A%22langchain%3D%3D1%22
Project-URL: Twitter, https://x.com/LangChainAI
Project-URL: Slack, https://www.langchain.com/join-community
Project-URL: Reddit, https://www.reddit.com/r/LangChain/
License: MIT
License-File: LICENSE
Requires-Python: <4.0.0,>=3.10.0
Requires-Dist: langchain-core<2.0.0,>=1.1.0
Requires-Dist: langgraph<1.1.0,>=1.0.2
Requires-Dist: pydantic<3.0.0,>=2.7.4
Provides-Extra: anthropic
Requires-Dist: langchain-anthropic; extra == 'anthropic'
Provides-Extra: aws
Requires-Dist: langchain-aws; extra == 'aws'
Provides-Extra: azure-ai
Requires-Dist: langchain-azure-ai; extra == 'azure-ai'
Provides-Extra: community
Requires-Dist: langchain-community; extra == 'community'
Provides-Extra: deepseek
Requires-Dist: langchain-deepseek; extra == 'deepseek'
Provides-Extra: fireworks
Requires-Dist: langchain-fireworks; extra == 'fireworks'
Provides-Extra: google-genai
Requires-Dist: langchain-google-genai; extra == 'google-genai'
Provides-Extra: google-vertexai
Requires-Dist: langchain-google-vertexai; extra == 'google-vertexai'
Provides-Extra: groq
Requires-Dist: langchain-groq; extra == 'groq'
Provides-Extra: huggingface
Requires-Dist: langchain-huggingface; extra == 'huggingface'
Provides-Extra: mistralai
Requires-Dist: langchain-mistralai; extra == 'mistralai'
Provides-Extra: ollama
Requires-Dist: langchain-ollama; extra == 'ollama'
Provides-Extra: openai
Requires-Dist: langchain-openai; extra == 'openai'
Provides-Extra: perplexity
Requires-Dist: langchain-perplexity; extra == 'perplexity'
Provides-Extra: together
Requires-Dist: langchain-together; extra == 'together'
Provides-Extra: xai
Requires-Dist: langchain-xai; extra == 'xai'
